hpsim/__init__.py
hpsim/acceleration.py
hpsim/arena.py
hpsim/boundaries.py
hpsim/energy.py
hpsim/ensgen.py
hpsim/force.py
hpsim/hdf5gen.py
hpsim/integrator.py
hpsim/main.py
hpsim/maintest.py
hpsim/miscfuncs.py
hpsim/newmain.py
hpsim/ntgrtr.py
hpsim/solver.py
hpsim/sonic.py
hpsim/timegen.py
hpsim/timestep.py
hpsim/visual.py
hpsim-0.8.0.dist-info/LICENSE
hpsim-0.8.0.dist-info/METADATA
hpsim-0.8.0.dist-info/WHEEL
hpsim-0.8.0.dist-info/top_level.txt
hpsim-0.8.0.dist-info/RECORD
