Metadata-Version: 2.1
Name: hpsim
Version: 0.8.0
Summary: A modular, high performance particle simulator
Home-page: http://github.com/Hogbobson/hpsim
Author: Mads Kildholt
Author-email: hogbobson@gmail.com
License: GNU General Public License v3
Platform: UNKNOWN
